[
  {
    "id": "1",
    "code": "X7K9M2P4Q",
    "tariff": "Элегантный",
    "duration": "1 месяц",
    "discount": "10%",
    "isUnlimited": false,
    "usedCount": 0,
    "limit": 1,
    "isClient": true
  },
  {
    "id": "2",
    "code": "R5T8W3Y6Z",
    "tariff": "Уютный",
    "duration": "3 месяца",
    "discount": "20%",
    "isUnlimited": false,
    "usedCount": 1,
    "limit": 1,
    "isClient": true
  },
  {
    "id": "3",
    "code": "A9B2C7D4E",
    "tariff": "Особенный",
    "duration": "6 месяцев",
    "discount": "15%",
    "isUnlimited": true,
    "usedCount": 0,
    "limit": null,
    "isClient": true
  },
  {
    "id": "4",
    "code": "ADMIN2024",
    "tariff": "Элегантный",
    "duration": "1 месяц",
    "discount": "25%",
    "isUnlimited": true,
    "usedCount": 0,
    "limit": null,
    "isClient": false
  },
  {
    "id": "5",
    "code": "F3G6H9J1K",
    "tariff": "Уютный",
    "duration": "3 месяца",
    "discount": "10%",
    "isUnlimited": false,
    "usedCount": 1,
    "limit": 1,
    "isClient": true
  },
  {
    "id": "6",
    "code": "LOYALTY30",
    "tariff": "Особенный",
    "duration": "6 месяцев",
    "discount": "30%",
    "isUnlimited": true,
    "usedCount": 15,
    "limit": null,
    "isClient": false
  },
  {
    "id": "7",
    "code": "L8M4N7P2Q",
    "tariff": "Элегантный",
    "duration": "1 месяц",
    "discount": "15%",
    "isUnlimited": false,
    "usedCount": 0,
    "limit": 1,
    "isClient": true
  },
  {
    "id": "8",
    "code": "S5T9V1W4X",
    "tariff": "Уютный",
    "duration": "3 месяца",
    "discount": "20%",
    "isUnlimited": false,
    "usedCount": 1,
    "limit": 1,
    "isClient": true
  },
  {
    "id": "9",
    "code": "ADMIN50",
    "tariff": "Особенный",
    "duration": "6 месяцев",
    "discount": "50%",
    "isUnlimited": true,
    "usedCount": 8,
    "limit": null,
    "isClient": false
  },
  {
    "id": "10",
    "code": "Y2Z6A3B8C",
    "tariff": "Элегантный",
    "duration": "1 месяц",
    "discount": "5%",
    "isUnlimited": false,
    "usedCount": 1,
    "limit": 1,
    "isClient": true
  },
  {
    "id": "11",
    "code": "D4E7F1G5H",
    "tariff": "Уютный",
    "duration": "3 месяца",
    "discount": "25%",
    "isUnlimited": false,
    "usedCount": 0,
    "limit": 1,
    "isClient": true
  },
  {
    "id": "12",
    "code": "VIP40",
    "tariff": "Особенный",
    "duration": "6 месяцев",
    "discount": "40%",
    "isUnlimited": true,
    "usedCount": 23,
    "limit": null,
    "isClient": false
  },
  {
    "id": "13",
    "code": "I9J3K6L2M",
    "tariff": "Элегантный",
    "duration": "1 месяц",
    "discount": "12%",
    "isUnlimited": false,
    "usedCount": 1,
    "limit": 1,
    "isClient": true
  },
  {
    "id": "14",
    "code": "N5O8P1Q4R",
    "tariff": "Уютный",
    "duration": "3 месяца",
    "discount": "15%",
    "isUnlimited": false,
    "usedCount": 0,
    "limit": 1,
    "isClient": true
  },
  {
    "id": "15",
    "code": "ADMIN35",
    "tariff": "Особенный",
    "duration": "6 месяцев",
    "discount": "35%",
    "isUnlimited": true,
    "usedCount": 5,
    "limit": null,
    "isClient": false
  },
  {
    "id": "16",
    "code": "S7T2U5V9W",
    "tariff": "Элегантный",
    "duration": "1 месяц",
    "discount": "8%",
    "isUnlimited": false,
    "usedCount": 1,
    "limit": 1,
    "isClient": true
  },
  {
    "id": "17",
    "code": "X3Y6Z1A4B",
    "tariff": "Уютный",
    "duration": "3 месяца",
    "discount": "18%",
    "isUnlimited": false,
    "usedCount": 0,
    "limit": 1,
    "isClient": true
  },
  {
    "id": "18",
    "code": "PREMIUM45",
    "tariff": "Особенный",
    "duration": "6 месяцев",
    "discount": "45%",
    "isUnlimited": true,
    "usedCount": 12,
    "limit": null,
    "isClient": false
  },
  {
    "id": "19",
    "code": "C8D2E5F9G",
    "tariff": "Элегантный",
    "duration": "1 месяц",
    "discount": "10%",
    "isUnlimited": false,
    "usedCount": 1,
    "limit": 1,
    "isClient": true
  },
  {
    "id": "20",
    "code": "H3I7J1K4L",
    "tariff": "Уютный",
    "duration": "3 месяца",
    "discount": "22%",
    "isUnlimited": false,
    "usedCount": 0,
    "limit": 1,
    "isClient": true
  },
  {
    "id": "21",
    "code": "ADMIN60",
    "tariff": "Особенный",
    "duration": "6 месяцев",
    "discount": "60%",
    "isUnlimited": true,
    "usedCount": 3,
    "limit": null,
    "isClient": false
  },
  {
    "id": "22",
    "code": "M6N9O2P5Q",
    "tariff": "Элегантный",
    "duration": "1 месяц",
    "discount": "12%",
    "isUnlimited": false,
    "usedCount": 0,
    "limit": 1,
    "isClient": true
  },
  {
    "id": "23",
    "code": "R1S4T8U3V",
    "tariff": "Уютный",
    "duration": "3 месяца",
    "discount": "20%",
    "isUnlimited": false,
    "usedCount": 1,
    "limit": 1,
    "isClient": true
  },
  {
    "id": "24",
    "code": "SPECIAL30",
    "tariff": "Особенный",
    "duration": "6 месяцев",
    "discount": "30%",
    "isUnlimited": true,
    "usedCount": 7,
    "limit": null,
    "isClient": false
  },
  {
    "id": "25",
    "code": "W7X2Y5Z9A",
    "tariff": "Элегантный",
    "duration": "1 месяц",
    "discount": "5%",
    "isUnlimited": false,
    "usedCount": 1,
    "limit": 1,
    "isClient": true
  },
  {
    "id": "26",
    "code": "B4C8D1E6F",
    "tariff": "Уютный",
    "duration": "3 месяца",
    "discount": "25%",
    "isUnlimited": false,
    "usedCount": 0,
    "limit": 1,
    "isClient": true
  },
  {
    "id": "27",
    "code": "ADMIN55",
    "tariff": "Особенный",
    "duration": "6 месяцев",
    "discount": "55%",
    "isUnlimited": true,
    "usedCount": 0,
    "limit": null,
    "isClient": false
  },
  {
    "id": "28",
    "code": "G3H7I2J5K",
    "tariff": "Элегантный",
    "duration": "1 месяц",
    "discount": "15%",
    "isUnlimited": false,
    "usedCount": 0,
    "limit": 1,
    "isClient": true
  },
  {
    "id": "29",
    "code": "L9M3N6O1P",
    "tariff": "Уютный",
    "duration": "3 месяца",
    "discount": "20%",
    "isUnlimited": false,
    "usedCount": 1,
    "limit": 1,
    "isClient": true
  },
  {
    "id": "30",
    "code": "ULTRA50",
    "tariff": "Особенный",
    "duration": "6 месяцев",
    "discount": "50%",
    "isUnlimited": true,
    "usedCount": 19,
    "limit": null,
    "isClient": false
  }
]
